skanym/__init__.py
skanym/animators/__init__.py
skanym/animators/baseAnimator.py
skanym/animators/baseFkAnimator.py
skanym/animators/globalFkAnimator.py
skanym/animators/localFkAnimator.py
skanym/animators/pcaAnimator.py
skanym/animators/vaeAnimator.py
skanym/loaders/__init__.py
skanym/loaders/assimpLoader.py
skanym/loaders/iFileLoader.py
skanym/loaders/objectLoader.py
skanym/models/__init__.py
skanym/models/baseVae.py
skanym/models/conditionalVae.py
skanym/models/inputFormatter.py
skanym/structures/__init__.py
skanym/structures/animation/__init__.py
skanym/structures/animation/animation.py
skanym/structures/animation/animationCurve.py
skanym/structures/animation/iCurve.py
skanym/structures/animation/key.py
skanym/structures/animation/positionCurve.py
skanym/structures/animation/quaternionCurve.py
skanym/structures/animation/scalarCurve.py
skanym/structures/character/__init__.py
skanym/structures/character/joint.py
skanym/structures/character/skeleton.py
skanym/structures/data/__init__.py
skanym/structures/data/iTransform.py
skanym/structures/data/transform.py
skanym/structures/data/transformMatrix.py
skanym/structures/data/vectorizedArray.py
skanym/structures/network/vae.py
skanym/utils/__init__.py
skanym/utils/animationUtils.py
skanym/utils/character.py
skanym/utils/conversion.py
skanym/utils/metrics.py
skanym/utils/plots.py
skanym/utils/fbx_bindings/FbxCommon.py
skanym/utils/fbx_bindings/__init__.py
skanym/utils/fbx_bindings/fbx.pyd
skanym/utils/fbx_bindings/sip.pyd
skanym-0.1.6.dist-info/LICENSE.txt
skanym-0.1.6.dist-info/METADATA
skanym-0.1.6.dist-info/WHEEL
skanym-0.1.6.dist-info/top_level.txt
skanym-0.1.6.dist-info/RECORD
