Metadata-Version: 2.1
Name: skanym
Version: 0.1.6
Summary: Standalone package for skeletal animation
Author-email: Dimitri Kohler <dimitri.kohler@he-arc.ch>
License: MIT License
Project-URL: Repository, https://gitlab-etu.ing.he-arc.ch/isc/general/motion-machine/skanym-package/skanym
Classifier: Development Status :: 4 - Beta
Classifier: Intended Audience :: Developers
Classifier: Topic :: Software Development
Classifier: Programming Language :: Python :: 3.10
Requires-Python: ==3.10.*
License-File: LICENSE.txt
Requires-Dist: setuptools
Requires-Dist: wheel
Requires-Dist: numpy-quaternion >=2022.0.0
Requires-Dist: numpy
Requires-Dist: pyassimp ==5.2.5
Requires-Dist: scikit-learn ==1.4.1.post1
Provides-Extra: gui
Requires-Dist: skanym-gui ; extra == 'gui'
